pydra/tasks/mriqc/_version.py
pydra_mriqc-0.1.0.dist-info/METADATA
pydra_mriqc-0.1.0.dist-info/WHEEL
pydra_mriqc-0.1.0.dist-info/licenses/AUTHORS
pydra_mriqc-0.1.0.dist-info/licenses/LICENSE
pydra_mriqc-0.1.0.dist-info/licenses/NOTICE
pydra_mriqc-0.1.0.dist-info/RECORD
