Metadata-Version: 2.3
Name: pydra-mriqc
Version: 0.1.0
Summary: Pydra tasks package for mriqc
Author-email: Nipype developers <neuroimaging@python.org>
Maintainer-email: Nipype developers <neuroimaging@python.org>
License:    Copyright 2021 Nipype developers
License-File: AUTHORS
License-File: LICENSE
License-File: NOTICE
Keywords: pydra
Classifier: Development Status :: 2 - Pre-Alpha
Classifier: Environment :: Console
Classifier: Intended Audience :: Science/Research
Classifier: License :: OSI Approved :: Apache Software License
Classifier: Operating System :: MacOS :: MacOS X
Classifier: Operating System :: POSIX :: Linux
Classifier: Programming Language :: Python :: 3
Classifier: Topic :: Scientific/Engineering
Requires-Python: >=3.10
Requires-Dist: dipy
Requires-Dist: fileformats-datascience>=0.1
Requires-Dist: fileformats-medimage>=0.4.1
Requires-Dist: fileformats>=0.8.3
Requires-Dist: markupsafe~=2.0.1
Requires-Dist: matplotlib
Requires-Dist: migas>=0.4.0
Requires-Dist: nibabel
Requires-Dist: nilearn
Requires-Dist: pandas~=1.0
Requires-Dist: pydra-afni
Requires-Dist: pydra-ants
Requires-Dist: pydra-fsl
Requires-Dist: pydra-mrtrix3>=3.0.3a0
Requires-Dist: pydra-nireports
Requires-Dist: pydra-niworkflows
Requires-Dist: pydra>=0.22
Requires-Dist: pyyaml
Requires-Dist: scikit-learn
Requires-Dist: scipy
Requires-Dist: seaborn
Requires-Dist: statsmodels
Requires-Dist: templateflow
Requires-Dist: toml
Requires-Dist: tomli>=1.1.0; python_version < '3.11'
Requires-Dist: torch
Provides-Extra: dev
Requires-Dist: black; extra == 'dev'
Requires-Dist: pre-commit; extra == 'dev'
Provides-Extra: doc
Requires-Dist: packaging; extra == 'doc'
Requires-Dist: sphinx-rtd-theme; extra == 'doc'
Requires-Dist: sphinx>=2.1.2; extra == 'doc'
Requires-Dist: sphinxcontrib-apidoc~=0.3.0; extra == 'doc'
Requires-Dist: sphinxcontrib-napoleon; extra == 'doc'
Requires-Dist: sphinxcontrib-versioning; extra == 'doc'
Provides-Extra: test
Requires-Dist: codecov; extra == 'test'
Requires-Dist: fileformats-datascience-extras; extra == 'test'
Requires-Dist: fileformats-extras; extra == 'test'
Requires-Dist: fileformats-medimage-afni-extras; extra == 'test'
Requires-Dist: fileformats-medimage-extras; extra == 'test'
Requires-Dist: fileformats-medimage-fsl-extras; extra == 'test'
Requires-Dist: fileformats-medimage-mrtrix3-extras; extra == 'test'
Requires-Dist: nipype2pydra; extra == 'test'
Requires-Dist: pytest-cov; extra == 'test'
Requires-Dist: pytest-env; extra == 'test'
Requires-Dist: pytest-rerunfailures; extra == 'test'
Requires-Dist: pytest-xdist; extra == 'test'
Requires-Dist: pytest>=4.4.0; extra == 'test'
